{"id":59967,"cast":[{"cast_id":3,"character":"Joe","credit_id":"52fe49a5c3a36847f81a523f","id":24045,"name":"Joseph Gordon-Levitt","order":0,"profile_path":"/lrKBz4XR2Vxt5D56xrWOHvNZEIR.jpg"},{"cast_id":4,"character":"Older Joe","credit_id":"52fe49a5c3a36847f81a5243","id":62,"name":"Bruce Willis","order":1,"profile_path":"/kI1OluWhLJk3pnR19VjOfABpnTY.jpg"},{"cast_id":2,"character":"Sara","credit_id":"52fe49a5c3a36847f81a523b","id":5081,"name":"Emily Blunt","order":2,"profile_path":"/A3fiIXjP1xvDn4fESU2Hl7pfmuL.jpg"},{"cast_id":7,"character":"Seth","credit_id":"52fe49a5c3a36847f81a524f","id":17142,"name":"Paul Dano","order":3,"profile_path":"/qBIvuBoJ1EuBiDQ8NfJp4ljGMvp.jpg"},{"cast_id":26,"character":"Kid Blue","credit_id":"52fe49a5c3a36847f81a52b7","id":48312,"name":"Noah Segan","order":4,"profile_path":"/hxRWVwtxvzz0NTaaZMQwtPz8CDE.jpg"},{"cast_id":5,"character":"Suzie","credit_id":"52fe49a5c3a36847f81a5247","id":15555,"name":"Piper Perabo","order":5,"profile_path":"/50RVTSH3dmQYp8osJeogzOhQFyN.jpg"},{"cast_id":6,"character":"Abe","credit_id":"52fe49a5c3a36847f81a524b","id":8447,"name":"Jeff Daniels","order":6,"profile_path":"/vjn5pomAQOEQriemYxl6REQUX9Z.jpg"},{"cast_id":27,"character":"Cid","credit_id":"52fe49a5c3a36847f81a52bb","id":992427,"name":"Pierce Gagnon","order":7,"profile_path":"/unA3OndmjDgorhT055hjj2deAUl.jpg"},{"cast_id":28,"character":"Old Joe's Wife (as Summer Qing)","credit_id":"52fe49a5c3a36847f81a52bf","id":78879,"name":"Xu Qing","order":8,"profile_path":"/gRhCq9vBu8eLGKNWvmNbZ9xb1Z.jpg"},{"cast_id":8,"character":"Beatrix","credit_id":"52fe49a5c3a36847f81a5253","id":10580,"name":"Tracie Thoms","order":9,"profile_path":"/o52pNJgY0CsVOKj2abB3nIc5Dyy.jpg"},{"cast_id":29,"character":"Old Seth","credit_id":"52fe49a5c3a36847f81a52c3","id":565504,"name":"Frank Brennan","order":10,"profile_path":"/A1Z23UqiwBxX66iJTB4q9xjnG5P.jpg"},{"cast_id":30,"character":"Jesse","credit_id":"52fe49a5c3a36847f81a52c7","id":39520,"name":"Garret Dillahunt","order":11,"profile_path":"/72VwNIJ7s9LhdsDHTNdsbkEsVyK.jpg"},{"cast_id":31,"character":"Dale","credit_id":"52fe49a5c3a36847f81a52cb","id":84760,"name":"Nick Gomez","order":12,"profile_path":"/aBMQnvk2zayzgfWrp0rS0Ji1xIs.jpg"},{"cast_id":32,"character":"Zach","credit_id":"52fe49a5c3a36847f81a52cf","id":62076,"name":"Marcus Hester","order":13,"profile_path":"/mOlrvlDpYUzDJhG6yc2wiRCdH5X.jpg"},{"cast_id":33,"character":"Gat Man","credit_id":"52fe49a5c3a36847f81a52d3","id":231857,"name":"Jon Eyez","order":14,"profile_path":"/1v11aZ5TmwtORs10OcU4wzhX2NW.jpg"},{"cast_id":35,"character":"Gat Man","credit_id":"52fe49a5c3a36847f81a52dd","id":183099,"name":"Kevin Stillwell","order":15,"profile_path":null},{"cast_id":36,"character":"Gat Man","credit_id":"52fe49a5c3a36847f81a52e1","id":1132300,"name":"Thirl Haston","order":16,"profile_path":null},{"cast_id":37,"character":"Looper","credit_id":"52fe49a5c3a36847f81a52e5","id":1170659,"name":"James Landry Hébert","order":17,"profile_path":"/iFFAjpK2cvBTDpWXzyi7zaLSVUo.jpg"},{"cast_id":38,"character":"Looper","credit_id":"52fe49a5c3a36847f81a52e9","id":1088041,"name":"Kenneth Brown Jr.","order":18,"profile_path":"/kGGEedmcWvH1EpjyqEimH9pEgYn.jpg"},{"cast_id":39,"character":"Looper","credit_id":"52fe49a5c3a36847f81a52ed","id":1132301,"name":"Cody Wood","order":19,"profile_path":null},{"cast_id":40,"character":"Tye","credit_id":"52fe49a5c3a36847f81a52f1","id":111693,"name":"Adam Boyer","order":20,"profile_path":null},{"cast_id":41,"character":"Daniel","credit_id":"52fe49a5c3a36847f81a52f5","id":1271661,"name":"Kamden Beauchamp","order":21,"profile_path":null},{"cast_id":42,"character":"Neighbor Girl","credit_id":"52fe49a5c3a36847f81a52f9","id":1104568,"name":"Sylvia Jefferies","order":22,"profile_path":"/jtbJjvDrGAuBW3OGHSCGekuVo8J.jpg"},{"cast_id":43,"character":"Beggar Kid","credit_id":"530f4297925141736c000b03","id":1256260,"name":"Ian Patrick","order":23,"profile_path":"/53Dq8lug1bSWwlTRr7uzUzR5UpS.jpg"}],"crew":[{"credit_id":"52fe49a5c3a36847f81a5237","department":"Directing","id":67367,"job":"Director","name":"Rian Johnson","profile_path":"/pCdsaqBaG6SozL5HGwVRyIfjWtM.jpg"},{"credit_id":"52fe49a5c3a36847f81a5259","department":"Sound","id":69077,"job":"Original Music Composer","name":"Nathan Johnson","profile_path":null},{"credit_id":"52fe49a5c3a36847f81a525f","department":"Camera","id":59667,"job":"Director of Photography","name":"Steve Yedlin","profile_path":null},{"credit_id":"52fe49a5c3a36847f81a5265","department":"Editing","id":7784,"job":"Editor","name":"Bob Ducsay","profile_path":null},{"credit_id":"52fe49a5c3a36847f81a526b","department":"Production","id":60047,"job":"Producer","name":"Ram Bergman","profile_path":null},{"credit_id":"52fe49a5c3a36847f81a5271","department":"Production","id":52159,"job":"Producer","name":"James D. Stern","profile_path":null},{"credit_id":"52fe49a5c3a36847f81a5277","department":"Production","id":20064,"job":"Executive Producer","name":"Julie Goldstein","profile_path":null},{"credit_id":"52fe49a5c3a36847f81a527d","department":"Production","id":24045,"job":"Executive Producer","name":"Joseph Gordon-Levitt","profile_path":"/lrKBz4XR2Vxt5D56xrWOHvNZEIR.jpg"},{"credit_id":"52fe49a5c3a36847f81a5283","department":"Production","id":62782,"job":"Executive Producer","name":"Douglas Hansen","profile_path":null},{"credit_id":"52fe49a5c3a36847f81a5289","department":"Production","id":224512,"job":"Executive Producer","name":"Dan Mintz","profile_path":"/5nqmZQSOioaOGCMnKBmgyI4k2p0.jpg"},{"credit_id":"52fe49a5c3a36847f81a528f","department":"Production","id":113826,"job":"Line Producer","name":"David Pomier","profile_path":null},{"credit_id":"52fe49a5c3a36847f81a5295","department":"Production","id":62775,"job":"Executive Producer","name":"Peter Schlessel","profile_path":null},{"credit_id":"52fe49a5c3a36847f81a529b","department":"Production","id":1024910,"job":"Casting","name":"Lindsay Graham","profile_path":null},{"credit_id":"52fe49a5c3a36847f81a52a1","department":"Production","id":5914,"job":"Casting","name":"Mary Vernieu","profile_path":null},{"credit_id":"52fe49a5c3a36847f81a52a7","department":"Art","id":4953,"job":"Production Design","name":"Ed Verreaux","profile_path":null},{"credit_id":"52fe49a5c3a36847f81a52ad","department":"Costume & Make-Up","id":15573,"job":"Costume Design","name":"Sharen Davis","profile_path":null},{"credit_id":"52fe49a5c3a36847f81a52b3","department":"Crew","id":1024912,"job":"Art Direction","name":"James A. Gelarden","profile_path":null},{"credit_id":"52fe49a5c3a36847f81a52d9","department":"Writing","id":67367,"job":"Writer","name":"Rian Johnson","profile_path":"/pCdsaqBaG6SozL5HGwVRyIfjWtM.jpg"}]}